ichubOpenApi/__init__.py
ichubOpenApi/client.py
ichubOpenApi/const.py
ichubOpenApi/request/__init__.py
ichubOpenApi/request/models.py
ichubOpenApi/request/requestBase.py
ichubOpenApi/sign/Md5.py
ichubOpenApi/sign/Passport.py
ichubOpenApi/sign/Rsa.py
ichubOpenApi/sign/__init__.py
ichub_openapi_sdk_python-1.0.6.dist-info/METADATA
ichub_openapi_sdk_python-1.0.6.dist-info/WHEEL
ichub_openapi_sdk_python-1.0.6.dist-info/top_level.txt
ichub_openapi_sdk_python-1.0.6.dist-info/RECORD
